{
    "default": {
        "persist.sys.miui_animator_sched.bigcores": "4-6",
        "persist.sys.miui_animator_sched.sched_threads": "2",
        "persist.sys.miui.sf_cores": "4-7",
        "persist.vendor.display.miui.composer_boost": "4-7",
        "persist.sys.miui_animator_sched.big_prime_cores": "4-7",
        "persist.sys.minfree_def": "73728,92160,110592,154832,482560,579072",
        "persist.sys.minfree_6g": "73728,92160,110592,258048,663552,903168",
        "persist.sys.minfree_8g": "73728,92160,110592,387072,1105920,1451520",
        "persist.sys.first.frame.accelerates": "true"
    },
    "android_15": {
        "persist.sys.miui_animator_sched.bigcores": "4-7",
        "persist.sys.miui_animator_sched.big_prime_cores": "4-7",
        "persist.vendor.display.miui.composer_boost": "4-7"
    }
}